synergy_dataset/__init__.py
synergy_dataset/__main__.py
synergy_dataset/_version.py
synergy_dataset/base.py
synergy_dataset-1.2.dist-info/LICENSE
synergy_dataset-1.2.dist-info/METADATA
synergy_dataset-1.2.dist-info/WHEEL
synergy_dataset-1.2.dist-info/entry_points.txt
synergy_dataset-1.2.dist-info/top_level.txt
synergy_dataset-1.2.dist-info/RECORD
