Metadata-Version: 2.1
Name: synergy-dataset
Version: 1.2
Summary: Python package for the SYNERGY dataset
Author-email: Jonathan de Bruin <asreview@uu.nl>
License: MIT
Classifier: Development Status :: 5 - Production/Stable
Classifier: License :: OSI Approved :: MIT License
Classifier: Programming Language :: Python :: 3.7
Classifier: Programming Language :: Python :: 3.8
Classifier: Programming Language :: Python :: 3.9
Classifier: Programming Language :: Python :: 3.10
Classifier: Programming Language :: Python :: 3.11
Requires-Python: >=3.7
Provides-Extra: lint
Provides-Extra: test
License-File: LICENSE
